ac4y_object/__init__.py
ac4y_object/ac4y_object.py
ac4y_object-1.1.20220306.1.dist-info/LICENSE
ac4y_object-1.1.20220306.1.dist-info/METADATA
ac4y_object-1.1.20220306.1.dist-info/WHEEL
ac4y_object-1.1.20220306.1.dist-info/top_level.txt
ac4y_object-1.1.20220306.1.dist-info/RECORD
