Metadata-Version: 2.1
Name: ac4y-object
Version: 1.1.20220306.1
Summary: ac4y base object
Home-page: https://github.com/ac4y/PYAc4yObject
Author: ac4y
Author-email: appcloud4you@gmail.com
License: UNKNOWN
Project-URL: Bug Tracker, https://github.com/ac4y/PYAc4yObject/issues
Platform: UNKNOWN
Classifier: Programming Language :: Python :: 3
Classifier: License :: OSI Approved :: MIT License
Classifier: Operating System :: OS Independent
Requires-Python: >=3.6
License-File: LICENSE
